pytelog/__init__.py
pytelog/formatters.py
pytelog/handlers.py
pytelog-0.1.dist-info/LICENSE
pytelog-0.1.dist-info/METADATA
pytelog-0.1.dist-info/WHEEL
pytelog-0.1.dist-info/top_level.txt
pytelog-0.1.dist-info/RECORD
