Metadata-Version: 2.1
Name: pytelog
Version: 0.1
Summary: Python telegram logger
Home-page: https://github.com/sandino/pytelog
Author: sandino
Author-email: vladts77@gmail.com
License: UNKNOWN
Platform: UNKNOWN
Classifier: License :: OSI Approved :: MIT License
Classifier: Operating System :: OS Independent
Classifier: Programming Language :: Python :: 3
Requires-Python: >=3.6
Requires-Dist: requests
